<stars signature="BLbs1F6yhHMtP5BY3NzBdLKn3MbQEQ9ObaiqXBSUpXn7">
  <star>
    <pos>
      <x>154.348</x>
      <y>115.456</y>
    </pos>
    <color>
      <red>193</red>
      <green>175</green>
      <blue>203</blue>
    </color>
    <size>3</size>
    <power>68</power>
    <date />
    <info>no info</info>
  </star>
  <star>
    <pos>
      <x>98.7039</x>
      <y>70.0765</y>
    </pos>
    <color>
      <red>140</red>
      <green>151</green>
      <blue>107</blue>
    </color>
    <size>3</size>
    <power>54</power>
    <date />
    <info>no info</info>
  </star>
  <star>
    <pos>
      <x>204.248</x>
      <y>166.149</y>
    </pos>
    <color>
      <red>244</red>
      <green>199</green>
      <blue>203</blue>
    </color>
    <size>3</size>
    <power>45</power>
    <date />
    <info>no info</info>
  </star>
  <star>
    <pos>
      <x>188.492</x>
      <y>96.9179</y>
    </pos>
    <color>
      <red>247</red>
      <green>200</green>
      <blue>189</blue>
    </color>
    <size>3</size>
    <power>70</power>
    <date />
    <info>no info</info>
  </star>
  <star>
    <pos>
      <x>190.494</x>
      <y>104.438</y>
    </pos>
    <color>
      <red>142</red>
      <green>145</green>
      <blue>127</blue>
    </color>
    <size>3</size>
    <power>99</power>
    <date />
    <info>no info</info>
  </star>
  <star>
    <pos>
      <x>181.937</x>
      <y>98.365</y>
    </pos>
    <color>
      <red>207</red>
      <green>213</green>
      <blue>160</blue>
    </color>
    <size>3</size>
    <power>90</power>
    <date />
    <info>no info</info>
  </star>
  <star>
    <pos>
      <x>159.759</x>
      <y>120.178</y>
    </pos>
    <color>
      <red>185</red>
      <green>190</green>
      <blue>189</blue>
    </color>
    <size>3</size>
    <power>60</power>
    <date />
    <info>no info</info>
  </star>
  <star>
    <pos>
      <x>140.484</x>
      <y>160.054</y>
    </pos>
    <color>
      <red>243</red>
      <green>193</green>
      <blue>202</blue>
    </color>
    <size>3</size>
    <power>48</power>
    <date />
    <info>no info</info>
  </star>
</stars>